{
	"11165": {
		"name": "herb",
		"tags": "leafy greens"
	},
	"11005": {
		"name": "arrowhead",
		"tags": "leafy greens"
	},
	"11109": {
		"name": "Cabbage",
		"tags": "leafy greens"
	},
	"11116": {
		"name": "Cabbage, chinese (pak-choi)",
		"tags": "leafy greens"
	},
	"11147": {
		"name": "Chard, swiss",
		"tags": "leafy greens"
	},
	"11161": {
		"name": "Collards",
		"tags": "leafy greens"
	},
	"11233": {
		"name": "kale",
		"tags": "leafy greens"
	},
	"11251": {
		"name": "romaine",
		"tags": "leafy greens"
	},
	"11008": {
		"name": "artichoke",
		"tags": "vegetable"
	},
	"11011": {
		"name": "Asparagus",
		"tags": "vegetable"
	},
	"11205": {
		"name": "cucumber",
		"tags": "vegetable"
	},
	"11212": {
		"name": "edamame",
		"tags": "vegetable"
	},
	"11333": {
		"name": "bell pepper",
		"tags": "vegetable"
	},
	"11457": {
		"name": "spinach",
		"tags": "leafy greens"
	},
	"11422": {
		"name": "pumpkin",
		"tags": "squash"
	},
	"11467": {
		"name": "crookneck squash",
		"tags": "squash"
	},
	"11475": {
		"name": "scallop squash",
		"tags": "squash"
	},
	"11477": {
		"name": "zucchini",
		"tags": "vegetable"
	},
	"11482": {
		"name": "acorn squash",
		"tags": "squash"
	},
	"11485": {
		"name": "butternut squash",
		"tags": "squash"
	},
	"11489": {
		"name": "hubbard squash",
		"tags": "squash"
	},
	"11492": {
		"name": "spagetti squash",
		"tags": "squash"
	},
	"11508": {
		"name": "sweet potato",
		"tags": "starch"
	},
	"11529": {
		"name": "tomato",
		"tags": "vegetable"
	},
	"11591": {
		"name": "Watercress",
		"tags": "leafy greens"
	},
	"11674": {
		"name": "potato",
		"tags": "starch"
	},
	"11953": {
		"name": "zucchini",
		"tags": "squash"
	},
	"11959": {
		"name": "Arugula",
		"tags": "leafy greens"
	},
	"12006": {
		"name": "chia",
		"tags": "seed,nut"
	},
	"12023": {
		"name": "sesame",
		"tags": "seed"
	},
	"12036": {
		"name": "sunflower seeds",
		"tags": "seed"
	},
	"12061": {
		"name": "almond",
		"tags": "seed,nut"
	},
	"12078": {
		"name": "brazil nut",
		"tags": "nut"
	},
	"12087": {
		"name": "cashew",
		"tags": "seed,nut"
	},
	"12147": {
		"name": "pine nut",
		"tags": "nut"
	},
	"12151": {
		"name": "pistachio",
		"tags": "seed,nut"
	},
	"12155": {
		"name": "walnut",
		"tags": "nut"
	},
	"12163": {
		"name": "pumpkin seed",
		"tags": "seed"
	},
	"12220": {
		"name": "flaxseed",
		"tags": "seed"
	},
	"13317": {
		"name": "beef",
		"tags": "meat"
	},
	"13496": {
		"name": "70% lean beef",
		"tags": "meat,beef"
	},
	"14639": {
		"name": "milk (rice)",
		"tags": "milk,rice"
	},
	"15016": {
		"name": "cod",
		"tags": "fish"
	},
	"15040": {
		"name": "herring",
		"tags": "fish"
	},
	"15047": {
		"name": "mackerel",
		"tags": "fish"
	},
	"15088": {
		"name": "sardine",
		"tags": "fish"
	},
	"15118": {
		"name": "tuna",
		"tags": "fish"
	},
	"15212": {
		"name": "salmon",
		"tags": "fish"
	},
	"15240": {
		"name": "trout",
		"tags": "fish"
	},
	"16015": {
		"name": "black beans",
		"tags": "legume"
	},
	"16025": {
		"name": "great northern beans",
		"tags": "legume"
	},
	"16028": {
		"name": "kidney beans",
		"tags": "legume"
	},
	"16043": {
		"name": "pinto bean",
		"tags": "legume"
	},
	"16057": {
		"name": "chickpea",
		"tags": "legume"
	},
	"16063": {
		"name": "blackeye",
		"tags": "legume"
	},
	"16070": {
		"name": "lentils",
		"tags": "legume"
	},
	"16072": {
		"name": "lima bean",
		"tags": "legume"
	},
	"16081": {
		"name": "mung beans",
		"tags": "legume"
	},
	"16111": {
		"name": "soybean",
		"tags": "legume"
	},
	"16120": {
		"name": "milk (soy)",
		"tags": "milk,soy"
	},
	"16390": {
		"name": "peanut",
		"tags": "legume"
	},
	"16427": {
		"name": "tofu",
		"tags": "vegetable,soy"
	},
	"18069": {
		"name": "white bread",
		"tags": "starch"
	},
	"18075": {
		"name": "whole wheat bread",
		"tags": "starch"
	},
	"19293": {
		"name": "yogurt (frozen vanilla)",
		"tags": "dairy,yogurt"
	},
	"20037": {
		"name": "rice (brown)",
		"tags": "starch"
	},
	"23569": {
		"name": "85% lean beef",
		"tags": "meat,beef"
	},
	"43476": {
		"name": "yogurt (soy/tofu)",
		"tags": "yogurt,soy"
	},
	"43597": {
		"name": "cheese (mozzarella",
		"tags": "dairy,cheese"
	},
	"01174": {
		"name": "milk (2%)",
		"tags": "dairy,milk"
	},
	"01151": {
		"name": "milk (skim/nonfat)",
		"tags": "dairy,milk"
	},
	"01256": {
		"name": "yogurt (nonfat greek)",
		"tags": "dairy,yogurt"
	},
	"01009": {
		"name": "cheese (cheddar)",
		"tags": "dairy,cheese"
	},
	"01040": {
		"name": "cheese (swiss)",
		"tags": "dairy,cheese"
	},
	"01032": {
		"name": "cheese (parmesan)",
		"tags": "dairy,cheese"
	},
	"01019": {
		"name": "cheese (feta)",
		"tags": "dairy,cheese"
	},
	"01128": {
		"name": "egg",
		"tags": "egg,meat"
	},
	"05306": {
		"name": "ground turkey",
		"tags": "meat,poultry"
	},
	"05326": {
		"name": "chicken breast",
		"tags": "meat,poultry"
	},
	"09193": {
		"name": "olive",
		"tags": "vegetable"
	},
	"09037": {
		"name": "avocado",
		"tags": "vegetable"
	},
	"04545": {
		"name": "sunflower",
		"tags": "oil"
	},
	"04047": {
		"name": "cocconut",
		"tags": "oil"
	},
	"04055": {
		"name": " tomatoseed",
		"tags": "oil"
	},
	"04528": {
		"name": " walnut",
		"tags": "oil"
	},
	"04529": {
		"name": " almond",
		"tags": "oil"
	},
	"04532": {
		"name": "  hazelnut",
		"tags": "oil"
	},
	"04583": {
		"name": "  mustard",
		"tags": "oil"
	},
	"04588": {
		"name": "  oat",
		"tags": "oil"
	},
	"04589": {
		"name": "  Fish oil, cod liver",
		"tags": "oil"
	},
	"04590": {
		"name": "  Fish oil, herring",
		"tags": "oil"
	},
	"04591": {
		"name": "  Fish oil, menhaden",
		"tags": "oil"
	},
	"04594": {
		"name": " Fish oil, sardine",
		"tags": "oil"
	},
	"04506": {
		"name": " sunflower",
		"tags": "oil"
	},
	"04515": {
		"name": "palm",
		"tags": "oil"
	},
	"04002": {
		"name": "lard",
		"tags": "oil"
	},
	"04053": {
		"name": "olive",
		"tags": "oil"
	},
	"04582": {
		"name": "canola",
		"tags": "oil"
	},
	"04514": {
		"name": "poppyseed",
		"tags": "oil"
	},
	"04517": {
		"name": " grapeseed",
		"tags": "oil"
	},
	"04581": {
		"name": "avocado",
		"tags": "oil"
	},
	"42231": {
		"name": "Oil, flaxseed, cold pressed",
		"tags": "oil"
	},
	"04058": {
		"name": "sesame",
		"tags": "oil"
	},
	"04042": {
		"name": "peanut",
		"tags": "oil"
	}
}
